wdnas_client/__init__.py
wdnas_client/const.py
wdnas_client/exceptions.py
wdnas_client-0.9.4.dist-info/licenses/LICENSE
wdnas_client-0.9.4.dist-info/METADATA
wdnas_client-0.9.4.dist-info/WHEEL
wdnas_client-0.9.4.dist-info/top_level.txt
wdnas_client-0.9.4.dist-info/RECORD
