Metadata-Version: 2.4
Name: wdnas_client
Version: 0.9.4
License-File: LICENSE
Requires-Dist: aiohttp>=3.12.14
Dynamic: description
Dynamic: description-content-type
Dynamic: license-file
Dynamic: requires-dist
